README.md
setup.cfg
setup.py
hostcheck/__init__.py
hostcheck/main.py
hostcheck.egg-info/PKG-INFO
hostcheck.egg-info/SOURCES.txt
hostcheck.egg-info/dependency_links.txt
hostcheck.egg-info/requires.txt
hostcheck.egg-info/top_level.txt