Metadata-Version: 2.1
Name: hostcheck
Version: 0.0.4
Summary: A tool for checking host for work: http, tcp, ping, dns
Home-page: https://github.com/mishakorzik/hostcheck
Author: MishaKorzhik_He1Zen
Author-email: developer.mishakorzhik@gmail.com
License: Apache 2.0
Project-URL: Bug Tracker, https://github.com/mishakorzik/hostcheck/issues
Project-URL: Sponsor, https://www.buymeacoffee.com/misakorzik
Keywords: host,ip,tcp,http,ping,python,pypi,check-host,checkhost,check,info,domain,address,tools
Classifier: Development Status :: 5 - Production/Stable
Classifier: License :: OSI Approved :: Apache Software License
Classifier: Natural Language :: English
Classifier: Operating System :: OS Independent
Classifier: Programming Language :: Python
Classifier: Programming Language :: Python :: 3
Classifier: Programming Language :: Python :: 3.6
Classifier: Programming Language :: Python :: 3.7
Classifier: Programming Language :: Python :: 3.8
Classifier: Programming Language :: Python :: 3.9
Classifier: Programming Language :: Python :: 3.10
Classifier: Programming Language :: Python :: 3.11
Classifier: Programming Language :: Python :: 3 :: Only
Classifier: Programming Language :: Python :: Implementation :: CPython
Classifier: Programming Language :: Python :: Implementation :: PyPy
Classifier: Topic :: Internet
Classifier: Topic :: Software Development :: Libraries
Requires-Python: >=3.6
